LICENSE
README.md
setup.py
codectrl/__init__.py
codectrl.egg-info/PKG-INFO
codectrl.egg-info/SOURCES.txt
codectrl.egg-info/dependency_links.txt
codectrl.egg-info/requires.txt
codectrl.egg-info/top_level.txt