Metadata-Version: 2.1
Name: codectrl
Version: 0.1.7
Summary: A python logger module for the codeCTRL application
Home-page: UNKNOWN
Author: pwnCTRL
Author-email: contact@pwnctrl.com
License: MIT
Keywords: pwnCTRL,codeCTRL,logging,source code analysis,source code,analysis,security,vulnerability research
Platform: UNKNOWN
Classifier: Development Status :: 4 - Beta
Classifier: Intended Audience :: Developers
Classifier: Programming Language :: Python :: 3.9
Classifier: Operating System :: Unix
Classifier: Operating System :: MacOS :: MacOS X
Classifier: Operating System :: Microsoft :: Windows
License-File: LICENSE
